scrapli_paramiko/__init__.py
scrapli_paramiko/transport/__init__.py
scrapli_paramiko/transport/miko.py
tests/__init__.py
tests/unit/__init__.py
tests/unit/transport/__init__.py
tests/unit/transport/test_miko.py
scrapli_paramiko-2020.10.10.dist-info/LICENSE
scrapli_paramiko-2020.10.10.dist-info/METADATA
scrapli_paramiko-2020.10.10.dist-info/WHEEL
scrapli_paramiko-2020.10.10.dist-info/top_level.txt
scrapli_paramiko-2020.10.10.dist-info/RECORD
