Metadata-Version: 2.1
Name: scrapli-paramiko
Version: 2020.10.10
Summary: paramiko transport plugin for the scrapli SSH|Telnet screen scraping library
Home-page: https://github.com/scrapli/scrapli_paramiko
Author: Carl Montanari
Author-email: carl.r.montanari@gmail.com
License: UNKNOWN
Platform: UNKNOWN
Classifier: License :: OSI Approved :: MIT License
Classifier: Programming Language :: Python :: 3
Classifier: Programming Language :: Python :: 3.6
Classifier: Programming Language :: Python :: 3.7
Classifier: Programming Language :: Python :: 3.8
Classifier: Programming Language :: Python :: 3.9
Classifier: Operating System :: POSIX :: Linux
Classifier: Operating System :: MacOS
Requires-Python: >=3.6
Requires-Dist: paramiko (<3.0.0,>=2.6.0)
Requires-Dist: scrapli (>=2020.10.10)
